rocket_token/__init__.py
rocket_token/cli.py
rocket_token/exceptions.py
rocket_token/token.py
rocket_token-3.0.0.dist-info/LICENSE
rocket_token-3.0.0.dist-info/METADATA
rocket_token-3.0.0.dist-info/WHEEL
rocket_token-3.0.0.dist-info/entry_points.txt
rocket_token-3.0.0.dist-info/top_level.txt
rocket_token-3.0.0.dist-info/RECORD
