Metadata-Version: 2.1
Name: rocket-token
Version: 3.0.0
Summary: Generate tokens for use in the Adzooma platform.
Home-page: UNKNOWN
Author: Kieran Lavelle <kieran@clicktech.com>, Michael Brown <michael.b@clicktech.com>
License: MIT
Platform: UNKNOWN
License-File: LICENSE
Requires-Dist: cryptography (==3.4.7)
Requires-Dist: click
